{
  "$schema": "http://json-schema.org/draft-04/schema#",
  "type": "object",
  "title": "Pack Manifest Schema",
  "description": "Schema for pack_manifest.json in Minecraft Add-Ons",
  "definitions": {
    "terrain_texture": {
      "$ref": "terrain_texture.json#"
    },
    "item_texture": {
      "$ref": "item_texture.json#"
    },
    "flipbook_textures": {
      "$ref": "flipbook_textures.json#"
    }
  },
  "required": [
    "terrain_texture",
    "item_texture",
    "flipbook_textures"
  ]
}